.gitignore
MANIFEST.in
README.txt
setup.cfg
setup.py
docs/HISTORY.txt
docs/LICENSE.GPL
docs/LICENSE.txt
docs/frontpage.png
docs/portlets.png
docs/readiness.png
docs/sitemap.png
gomobile/__init__.py
gomobile.mobile.egg-info/PKG-INFO
gomobile.mobile.egg-info/SOURCES.txt
gomobile.mobile.egg-info/dependency_links.txt
gomobile.mobile.egg-info/entry_points.txt
gomobile.mobile.egg-info/namespace_packages.txt
gomobile.mobile.egg-info/not-zip-safe
gomobile.mobile.egg-info/requires.txt
gomobile.mobile.egg-info/top_level.txt
gomobile/mobile/__init__.py
gomobile/mobile/assignable.py
gomobile/mobile/behaviors.py
gomobile/mobile/configure.zcml
gomobile/mobile/discriminator.py
gomobile/mobile/interfaces.py
gomobile/mobile/locationmanager.py
gomobile/mobile/monkeypatch.py
gomobile/mobile/postpublication.py
gomobile/mobile/profiles.zcml
gomobile/mobile/rebuild_i18n.sh
gomobile/mobile/redirector.py
gomobile/mobile/setuphandlers.py
gomobile/mobile/sniffer.py
gomobile/mobile/utilities.py
gomobile/mobile/Extensions/Install.py
gomobile/mobile/browser/__init__.py
gomobile/mobile/browser/configure.zcml
gomobile/mobile/browser/forms.py
gomobile/mobile/browser/imageprocessor.py
gomobile/mobile/browser/resizer.py
gomobile/mobile/browser/sitemap.py
gomobile/mobile/browser/utilities.py
gomobile/mobile/browser/views.py
gomobile/mobile/browser/portlets/__init__.py
gomobile/mobile/browser/portlets/configure.zcml
gomobile/mobile/browser/portlets/preview.pt
gomobile/mobile/browser/portlets/preview.py
gomobile/mobile/browser/templates/mobile-sitemap.pt
gomobile/mobile/browser/templates/mobilesimulatoriframe.pt
gomobile/mobile/i18n/gomobile.mobile-plone-en.po
gomobile/mobile/i18n/gomobile.mobile-plone-es.po
gomobile/mobile/i18n/gomobile.mobile-plone-fi.po
gomobile/mobile/i18n/gomobile.mobile-plone.pot
gomobile/mobile/locales/gomobile.mobile.pot
gomobile/mobile/locales/en/LC_MESSAGES/gomobile.mobile.mo
gomobile/mobile/locales/en/LC_MESSAGES/gomobile.mobile.po
gomobile/mobile/locales/es/LC_MESSAGES/gomobile.mobile.mo
gomobile/mobile/locales/es/LC_MESSAGES/gomobile.mobile.po
gomobile/mobile/locales/fi/LC_MESSAGES/gomobile.mobile.mo
gomobile/mobile/locales/fi/LC_MESSAGES/gomobile.mobile.po
gomobile/mobile/profiles/default/actionicons.xml
gomobile/mobile/profiles/default/actions.xml
