Metadata-Version: 1.1
Name: gomobile.mobile
Version: 1.0.6
Summary: Core package for mobilizing Plone CMS
Home-page: http://webandmobile.mfabrik.com
Author: mFabrik Reseacrh Oy
Author-email: research@mfabrik.com
License: GPL
Keywords: mobile sniffer cms WAP plone
Platform: UNKNOWN
Classifier: Programming Language :: Python
Classifier: Topic :: Software Development :: Libraries :: Python Modules
Classifier: License :: OSI Approved :: GNU General Public License (GPL)
Classifier: Framework :: Plone
Classifier: Intended Audience :: Developers
